sysml2py/__init__.py
sysml2py/definition.py
sysml2py/formatting.py
sysml2py/grammar/KerML.tx
sysml2py/grammar/KerMLExpressions.tx
sysml2py/grammar/SysML.tx
sysml2py/grammar/SysML_compiled.tx
sysml2py/grammar/classes.py
sysml2py/textx/KerML.xtext
sysml2py/textx/KerMLExpressions.xtext
sysml2py/textx/SysML.xtext
sysml2py/textx/xtext_to_textx.py
sysml2py/usage.py
sysml2py-0.5.2.dist-info/LICENSE
sysml2py-0.5.2.dist-info/METADATA
sysml2py-0.5.2.dist-info/WHEEL
sysml2py-0.5.2.dist-info/RECORD
