Metadata-Version: 2.1
Name: sysml2py
Version: 0.5.2
Summary: 
Author: Christopher Cox
Author-email: chris.cox@westfall.io
Requires-Python: >=3.9,<4.0
Classifier: Programming Language :: Python :: 3
Classifier: Programming Language :: Python :: 3.9
Classifier: Programming Language :: Python :: 3.10
Classifier: Programming Language :: Python :: 3.11
Requires-Dist: astropy (>=5.3.1,<6.0.0)
Requires-Dist: pyyaml (>=6.0.1,<7.0.0)
Requires-Dist: textx (>=3.1.1,<4.0.0)
